LICENSE
README.md
setup.py
gridnet/__init__.py
gridnet/models.py
gridnet/train.py
gridnet/utils.py
gridnet_learn.egg-info/PKG-INFO
gridnet_learn.egg-info/SOURCES.txt
gridnet_learn.egg-info/dependency_links.txt
gridnet_learn.egg-info/requires.txt
gridnet_learn.egg-info/top_level.txt